odoo/addons/stock_picking_return_lot/README.rst
odoo/addons/stock_picking_return_lot/__init__.py
odoo/addons/stock_picking_return_lot/__manifest__.py
odoo/addons/stock_picking_return_lot/i18n/it.po
odoo/addons/stock_picking_return_lot/i18n/stock_picking_return_lot.pot
odoo/addons/stock_picking_return_lot/readme/CONTRIBUTORS.md
odoo/addons/stock_picking_return_lot/readme/DESCRIPTION.md
odoo/addons/stock_picking_return_lot/readme/USAGE.md
odoo/addons/stock_picking_return_lot/static/description/icon.png
odoo/addons/stock_picking_return_lot/static/description/index.html
odoo/addons/stock_picking_return_lot/tests/__init__.py
odoo/addons/stock_picking_return_lot/tests/test_stock_picking_return_lot.py
odoo/addons/stock_picking_return_lot/wizards/__init__.py
odoo/addons/stock_picking_return_lot/wizards/stock_return_picking.py
odoo/addons/stock_picking_return_lot/wizards/stock_return_picking.xml
odoo/addons/stock_picking_return_lot/wizards/stock_return_picking_line.py
odoo_addon_stock_picking_return_lot-18.0.1.0.0.2.dist-info/METADATA
odoo_addon_stock_picking_return_lot-18.0.1.0.0.2.dist-info/WHEEL
odoo_addon_stock_picking_return_lot-18.0.1.0.0.2.dist-info/top_level.txt
odoo_addon_stock_picking_return_lot-18.0.1.0.0.2.dist-info/RECORD
