Metadata-Version: 2.1
Name: odoo-addon-stock_picking_return_lot
Version: 18.0.1.0.0.2
Requires-Python: >=3.10
Requires-Dist: odoo-addon-stock_picking_return_restricted_qty==18.0.*
Requires-Dist: odoo-addon-stock_restrict_lot==18.0.*
Requires-Dist: odoo==18.0.*
Summary: Propagate SN/lots from origin picking to return picking.
Home-page: https://github.com/OCA/stock-logistics-workflow
License: AGPL-3
Author: Camptocamp, ACSONE SA/NV, Odoo Community Association (OCA)
Author-email: support@odoo-community.org
Classifier: Programming Language :: Python
Classifier: Framework :: Odoo
Classifier: Framework :: Odoo :: 18.0
Classifier: License :: OSI Approved :: GNU Affero General Public License v3
